aiopykube/__init__.py
aiopykube-0.1.0.dist-info/LICENSE
aiopykube-0.1.0.dist-info/WHEEL
aiopykube-0.1.0.dist-info/METADATA
aiopykube-0.1.0.dist-info/RECORD
