Metadata-Version: 2.1
Name: aiopykube
Version: 0.1.0
Summary: asyncio Pykube
License: MIT
Author: Thibaut Le Page
Author-email: thilp@thilp.net
Requires-Python: >=3.6,<4.0
Classifier: License :: OSI Approved :: MIT License
Classifier: Programming Language :: Python :: 3
Classifier: Programming Language :: Python :: 3.6
Classifier: Programming Language :: Python :: 3.7
